vedro_telemetry/__init__.py
vedro_telemetry/_send_request.py
vedro_telemetry/_utils.py
vedro_telemetry/_vedro_telemetry.py
vedro_telemetry/events.py
vedro_telemetry/py.typed
vedro_telemetry-0.3.0.dist-info/LICENSE
vedro_telemetry-0.3.0.dist-info/METADATA
vedro_telemetry-0.3.0.dist-info/WHEEL
vedro_telemetry-0.3.0.dist-info/top_level.txt
vedro_telemetry-0.3.0.dist-info/RECORD
