Metadata-Version: 2.1
Name: vedro-telemetry
Version: 0.3.0
Summary: Vedro plugin for collecting and sending test telemetry to your self-hosted server
Home-page: https://github.com/vedro-universe/vedro-telemetry
Author: Nikita Tsvetkov
Author-email: tsv1@fastmail.com
License: Apache-2.0
Classifier: License :: OSI Approved :: Apache Software License
Classifier: Programming Language :: Python :: 3.8
Classifier: Programming Language :: Python :: 3.9
Classifier: Programming Language :: Python :: 3.10
Classifier: Programming Language :: Python :: 3.11
Classifier: Programming Language :: Python :: 3.12
Classifier: Typing :: Typed
Requires-Python: >=3.8
License-File: LICENSE
Requires-Dist: vedro<2.0,>=1.7
Requires-Dist: httpx<1.0,>=0.17
